<?xml version="1.0" encoding="UTF-8" standalone="no"?>
<benchmark>
    <results>
        <result>
            <name/>
            <description/>
            <passIndex>-1</passIndex>
            <sourceId>3dmark-autosave-20191225221108.3dmark-result</sourceId>
            <TimeSpyCustomCPUScore>0</TimeSpyCustomCPUScore>
            <TimeSpyCustom3DMarkScore>0</TimeSpyCustom3DMarkScore>
            <TimeSpyCustomGraphicsScore>3494</TimeSpyCustomGraphicsScore>
            <benchmarkRunId>906fd7a5-e68b-4b6e-8c9d-30e4f1577aab</benchmarkRunId>
        </result>
        <result>
            <name/>
            <description/>
            <passIndex>0</passIndex>
            <sourceId>3dmark-autosave-20191225221108.3dmark-result</sourceId>
            <TimeSpyCustomGraphicsScoreForPass>3494</TimeSpyCustomGraphicsScoreForPass>
            <TimeSpyCustomCPUScoreForPass>0</TimeSpyCustomCPUScoreForPass>
            <TimeSpyCustom3DMarkScoreForPass>0</TimeSpyCustom3DMarkScoreForPass>
            <TimeSpyCustomGraphicsTest1>21.56</TimeSpyCustomGraphicsTest1>
            <TimeSpyCustomGraphicsTest2>21.09</TimeSpyCustomGraphicsTest2>
            <benchmarkRunId>906fd7a5-e68b-4b6e-8c9d-30e4f1577aab</benchmarkRunId>
        </result>
    </results>
</benchmark>
