<?xml version="1.0" encoding="UTF-8" standalone="no"?>
<benchmark>
    <results>
        <result>
            <name/>
            <description/>
            <passIndex>-1</passIndex>
            <sourceId>3dmark-autosave-20200108123257.3dmark-result</sourceId>
            <TimeSpyCustomCPUScore>0</TimeSpyCustomCPUScore>
            <TimeSpyCustom3DMarkScore>0</TimeSpyCustom3DMarkScore>
            <TimeSpyCustomGraphicsScore>2108</TimeSpyCustomGraphicsScore>
            <benchmarkRunId>40207a16-38a3-4546-8ce5-6785b567f93a</benchmarkRunId>
        </result>
        <result>
            <name/>
            <description/>
            <passIndex>0</passIndex>
            <sourceId>3dmark-autosave-20200108123257.3dmark-result</sourceId>
            <TimeSpyCustomGraphicsScoreForPass>2108</TimeSpyCustomGraphicsScoreForPass>
            <TimeSpyCustomCPUScoreForPass>0</TimeSpyCustomCPUScoreForPass>
            <TimeSpyCustom3DMarkScoreForPass>0</TimeSpyCustom3DMarkScoreForPass>
            <TimeSpyCustomGraphicsTest1>12.92</TimeSpyCustomGraphicsTest1>
            <TimeSpyCustomGraphicsTest2>12.81</TimeSpyCustomGraphicsTest2>
            <benchmarkRunId>40207a16-38a3-4546-8ce5-6785b567f93a</benchmarkRunId>
        </result>
    </results>
</benchmark>
